pitchlense_mcp/__init__.py
pitchlense_mcp/cli.py
pitchlense_mcp/analyzers/__init__.py
pitchlense_mcp/analyzers/competitive_risk.py
pitchlense_mcp/analyzers/customer_risk.py
pitchlense_mcp/analyzers/exit_risk.py
pitchlense_mcp/analyzers/financial_risk.py
pitchlense_mcp/analyzers/legal_risk.py
pitchlense_mcp/analyzers/lv_analysis.py
pitchlense_mcp/analyzers/market_risk.py
pitchlense_mcp/analyzers/operational_risk.py
pitchlense_mcp/analyzers/peer_benchmark.py
pitchlense_mcp/analyzers/product_risk.py
pitchlense_mcp/analyzers/social_coverage_risk.py
pitchlense_mcp/analyzers/social_coverage_risk_mcp.py
pitchlense_mcp/analyzers/team_risk.py
pitchlense_mcp/core/__init__.py
pitchlense_mcp/core/base.py
pitchlense_mcp/core/comprehensive_scanner.py
pitchlense_mcp/core/gemini_client.py
pitchlense_mcp/core/mock_client.py
pitchlense_mcp/models/__init__.py
pitchlense_mcp/models/risk_models.py
pitchlense_mcp/prompts/__init__.py
pitchlense_mcp/prompts/risk_analysis_prompts.py
pitchlense_mcp/tools/__init__.py
pitchlense_mcp/tools/content_moderation.py
pitchlense_mcp/tools/knowledge_graph.py
pitchlense_mcp/tools/linkedin_analyzer.py
pitchlense_mcp/tools/lv_analysis_tool.py
pitchlense_mcp/tools/perplexity_search.py
pitchlense_mcp/tools/serp_news.py
pitchlense_mcp/tools/serp_pdf_search.py
pitchlense_mcp/tools/social_media_research.py
pitchlense_mcp/tools/upload_extractor.py
pitchlense_mcp/tools/vertex_ai_agent_builder.py
pitchlense_mcp/tools/vertex_ai_rag.py
pitchlense_mcp/utils/__init__.py
pitchlense_mcp/utils/json_extractor.py
pitchlense_mcp-1.1.7.dist-info/licenses/LICENSE
pitchlense_mcp-1.1.7.dist-info/METADATA
pitchlense_mcp-1.1.7.dist-info/WHEEL
pitchlense_mcp-1.1.7.dist-info/entry_points.txt
pitchlense_mcp-1.1.7.dist-info/top_level.txt
pitchlense_mcp-1.1.7.dist-info/RECORD
