Metadata-Version: 2.4
Name: pitchlense-mcp
Version: 1.1.7
Summary: Professional startup risk analysis using MCP and Google Gemini AI
Home-page: https://github.com/pitchlense/pitchlense-mcp
Author: Aman Ulla
Author-email: Aman Ulla <connectamanulla@gmail.com>
Maintainer-email: Aman Ulla <connectamanulla@gmail.com>
License: MIT
Project-URL: Homepage, https://pitchlense.com
Project-URL: Documentation, https://pitchlense-mcp.readthedocs.io/
Project-URL: Repository, https://github.com/pitchlense/pitchlense-mcp
Project-URL: Bug Tracker, https://github.com/pitchlense/pitchlense-mcp/issues
Keywords: startup,risk,analysis,investment,mcp,model-context-protocol,gemini,ai,machine-learning,due-diligence,venture-capital
Classifier: Development Status :: 5 - Production/Stable
Classifier: Intended Audience :: Financial and Insurance Industry
Classifier: Intended Audience :: Developers
Classifier: License :: OSI Approved :: MIT License
Classifier: Operating System :: OS Independent
Classifier: Programming Language :: Python :: 3
Classifier: Programming Language :: Python :: 3.8
Classifier: Programming Language :: Python :: 3.9
Classifier: Programming Language :: Python :: 3.10
Classifier: Programming Language :: Python :: 3.11
Classifier: Programming Language :: Python :: 3.12
Classifier: Topic :: Office/Business :: Financial :: Investment
Classifier: Topic :: Scientific/Engineering :: Artificial Intelligence
Classifier: Topic :: Software Development :: Libraries :: Python Modules
Requires-Python: >=3.8
License-File: LICENSE
Requires-Dist: fastmcp>=0.1.0
Requires-Dist: google-genai>=0.3.0
Requires-Dist: pydantic>=2.0.0
Requires-Dist: python-dotenv>=1.0.0
Requires-Dist: httpx>=0.25.0
Requires-Dist: requests>=2.28.0
Requires-Dist: typing-extensions>=4.0.0
Requires-Dist: google-search-results>=2.4.2
Provides-Extra: dev
Requires-Dist: pytest>=7.0.0; extra == "dev"
Requires-Dist: pytest-cov>=4.0.0; extra == "dev"
Requires-Dist: flake8>=6.0.0; extra == "dev"
Requires-Dist: mypy>=1.0.0; extra == "dev"
Requires-Dist: pre-commit>=3.0.0; extra == "dev"
Requires-Dist: isort>=5.12.0; extra == "dev"
Requires-Dist: truffleHog3>=3.0.10; extra == "dev"
Provides-Extra: docs
Requires-Dist: sphinx>=6.0.0; extra == "docs"
Requires-Dist: sphinx-rtd-theme>=1.2.0; extra == "docs"
Requires-Dist: myst-parser>=1.0.0; extra == "docs"
Dynamic: author
Dynamic: home-page
Dynamic: license-file
Dynamic: requires-python
